freeze/__init__.py
freeze/freeze.py
freeze/thaw.py
frz-0.0.2.dist-info/LICENSE
frz-0.0.2.dist-info/METADATA
frz-0.0.2.dist-info/WHEEL
frz-0.0.2.dist-info/top_level.txt
frz-0.0.2.dist-info/RECORD
