Metadata-Version: 2.1
Name: frz
Version: 0.0.2
Summary: Frozen implementations of your favorite collections.
Home-page: https://github.com/Lightricks/freeze
Author: Hagai Weinfeld
Author-email: hagai.weinfeld@gmail.com
License: UNKNOWN
Project-URL: Bug Tracker, https://github.com/Lightricks/freeze/issues
Platform: UNKNOWN
Classifier: Programming Language :: Python :: 3
Classifier: License :: OSI Approved :: MIT License
Classifier: Operating System :: OS Independent
Requires-Python: >=3.7
License-File: LICENSE
